stt_sample_inspector/__init__.py
stt_sample_inspector/cli.py
stt_sample_inspector/inspect.py
stt_sample_inspector/server.py
stt_sample_inspector/utils.py
stt_sample_inspector/sample_data/LDC93S1.wav
stt_sample_inspector/sample_data/ldc93s1.csv
stt_sample_inspector/static/bootstrap/bootstrap.min.css
stt_sample_inspector/static/fontawesome/css/fontawesome.min.css
stt_sample_inspector/static/fontawesome/css/solid.min.css
stt_sample_inspector/static/fontawesome/webfonts/fa-solid-900.eot
stt_sample_inspector/static/fontawesome/webfonts/fa-solid-900.svg
stt_sample_inspector/static/fontawesome/webfonts/fa-solid-900.ttf
stt_sample_inspector/static/fontawesome/webfonts/fa-solid-900.woff
stt_sample_inspector/static/fontawesome/webfonts/fa-solid-900.woff2
stt_sample_inspector/static/wavesurfer/wavesurfer.cursor.min.js
stt_sample_inspector/static/wavesurfer/wavesurfer.min.js
stt_sample_inspector/static/wavesurfer/wavesurfer.min.js.map
stt_sample_inspector/templates/inspect.html
stt_sample_inspector-0.0.1.dist-info/AUTHORS.rst
stt_sample_inspector-0.0.1.dist-info/LICENSE.txt
stt_sample_inspector-0.0.1.dist-info/METADATA
stt_sample_inspector-0.0.1.dist-info/WHEEL
stt_sample_inspector-0.0.1.dist-info/entry_points.txt
stt_sample_inspector-0.0.1.dist-info/top_level.txt
stt_sample_inspector-0.0.1.dist-info/RECORD
