Metadata-Version: 2.1
Name: stt-sample-inspector
Version: 0.0.1
Summary: Inspect, modify, and add metadata to DeepSpeech (speech-to-text) datasets in CSV format.
Home-page: https://github.com/reuben/stt_sample_inspector/
Author: Reuben Morais
Author-email: reuben.morais@gmail.com
License: mozilla
Project-URL: Documentation, https://github.com/reuben/stt_sample_inspector/
Platform: any
Classifier: Development Status :: 4 - Beta
Classifier: Programming Language :: Python
Requires-Python: >=3.6
License-File: LICENSE.txt
License-File: AUTHORS.rst
Requires-Dist: numpy
Requires-Dist: scipy
Requires-Dist: flask
Requires-Dist: pandas
Requires-Dist: librosa
Requires-Dist: matplotlib
Provides-Extra: testing
Requires-Dist: pytest ; extra == 'testing'
Requires-Dist: pytest-cov ; extra == 'testing'
